plone.app.relationfield-4.0.3-py3.13-nspkg.pth
plone/app/relationfield/__init__.py
plone/app/relationfield/adapter.py
plone/app/relationfield/behavior.py
plone/app/relationfield/configure.zcml
plone/app/relationfield/demo.py
plone/app/relationfield/demo.zcml
plone/app/relationfield/event.py
plone/app/relationfield/interfaces.py
plone/app/relationfield/marshaler.py
plone/app/relationfield/marshaler.rst
plone/app/relationfield/marshaler.zcml
plone/app/relationfield/monkey.py
plone/app/relationfield/path.py
plone/app/relationfield/schemaeditor.py
plone/app/relationfield/schemaeditor.txt
plone/app/relationfield/schemaeditor.zcml
plone/app/relationfield/schemaeditor_contenttree.txt
plone/app/relationfield/setuphandlers.py
plone/app/relationfield/source.py
plone/app/relationfield/supermodel.py
plone/app/relationfield/supermodel.txt
plone/app/relationfield/supermodel.zcml
plone/app/relationfield/supermodel_contenttree.txt
plone/app/relationfield/testing.py
plone/app/relationfield/widget.py
plone/app/relationfield/widget.zcml
plone/app/relationfield/profiles/default/install_relations.txt
plone/app/relationfield/profiles/default/metadata.xml
plone/app/relationfield/tests/__init__.py
plone/app/relationfield/tests/test_marshall.py
plone/app/relationfield/tests/test_marshall.zcml
plone/app/relationfield/tests/test_schemaeditor.py
plone/app/relationfield/tests/test_supermodel.py
plone/app/relationfield/tests/test_widget.py
plone_app_relationfield-4.0.3.dist-info/METADATA
plone_app_relationfield-4.0.3.dist-info/WHEEL
plone_app_relationfield-4.0.3.dist-info/namespace_packages.txt
plone_app_relationfield-4.0.3.dist-info/top_level.txt
plone_app_relationfield-4.0.3.dist-info/RECORD
