Metadata-Version: 2.4
Name: plone.app.relationfield
Version: 4.0.3
Summary: Plone support for z3c.relationfield
Home-page: https://pypi.org/project/plone.app.relationfield
Author: Alec Mitchell
Author-email: apm13@columbia.edu
License: GPL
Keywords: dexterity relations plone zc.relation
Classifier: Development Status :: 5 - Production/Stable
Classifier: Framework :: Plone
Classifier: Framework :: Plone :: 6.1
Classifier: Framework :: Plone :: Core
Classifier: License :: OSI Approved :: GNU General Public License (GPL)
Classifier: Programming Language :: Python
Classifier: Programming Language :: Python :: 3.8
Classifier: Programming Language :: Python :: 3.9
Classifier: Programming Language :: Python :: 3.10
Classifier: Programming Language :: Python :: 3.11
Classifier: Programming Language :: Python :: 3.12
Classifier: Topic :: Software Development :: Libraries :: Python Modules
Requires-Python: >=3.8
Requires-Dist: setuptools
Requires-Dist: plone.base
Requires-Dist: Products.CMFCore
Requires-Dist: five.intid
Requires-Dist: plone.app.intid
Requires-Dist: plone.app.vocabularies
Requires-Dist: plone.app.z3cform
Requires-Dist: plone.autoform
Requires-Dist: plone.behavior
Requires-Dist: plone.dexterity
Requires-Dist: plone.rfc822
Requires-Dist: plone.schemaeditor
Requires-Dist: plone.supermodel
Requires-Dist: plone.uuid
Requires-Dist: z3c.form
Requires-Dist: z3c.objpath
Requires-Dist: z3c.formwidget.query
Requires-Dist: z3c.relationfield
Requires-Dist: zc.relation
Requires-Dist: Zope
Requires-Dist: zope.intid
Provides-Extra: test
Requires-Dist: plone.app.contenttypes[test]; extra == "test"
Requires-Dist: plone.app.testing; extra == "test"
Requires-Dist: plone.app.dexterity; extra == "test"
Requires-Dist: plone.formwidget.contenttree; extra == "test"
Requires-Dist: plone.testing; extra == "test"
Dynamic: author
Dynamic: author-email
Dynamic: classifier
Dynamic: description
Dynamic: description-content-type
Dynamic: home-page
Dynamic: keywords
Dynamic: license
Dynamic: provides-extra
Dynamic: requires-dist
Dynamic: requires-python
Dynamic: summary
